{
    "configurations": [
        {
            "name": "Win32",
            "includePath": [
                "${workspaceFolder}/src/include/**",
                "/usr/include/x86_64-linux-gnu"
            ],
            "defines": [
                "_DEBUG",
                "UNICODE",
                "_UNICODE",
                "_GNU_SOURCE"
            ],
            "cStandard": "c89",
            "cppStandard": "c++17",
            "intelliSenseMode": "windows-msvc-x86",
            "compilerPath": "C:/msys64/mingw64/bin/gcc.exe",
            "compilerArgs": [],
            "mergeConfigurations": false,
            "browse": {
                "path": [
                    "${workspaceFolder}/src/include/**",
                    "${workspaceFolder}"
                ],
                "limitSymbolsToIncludedHeaders": true
            }
        },
        {
            "name": "Linux",
            "includePath": [
                "${workspaceFolder}/**",
                "${workspaceFolder}/src/include/**",
                "/usr/include/x86_64-linux-gnu",
                "/usr/include/linux",
                "/usr/lib/gcc/x86_64-linux-gnu/9/include/"
            ],
            "defines": [],
            "compilerPath": "/usr/bin/gcc",
            "cppStandard": "c++17",
            "intelliSenseMode": "linux-gcc-x64",
            "compilerArgs": [
                "--disable-multilib"
            ],
            "cStandard": "c89",
            "mergeConfigurations": false,
            "browse": {
                "path": [
                    "${workspaceFolder}/**"
                ],
                "limitSymbolsToIncludedHeaders": true
            }
        }
    ],
    "version": 4
}